pywallex/__init__.py
pywallex/abstract/__init__.py
pywallex/abstract/wallex_client.py
pywallex/host2host/__init__.py
pywallex/host2host/exchange.py
pywallex/host2host/payout.py
pywallex/host2host/swagger.yaml
pywallex/payout.py
pywallex/schemas.py
pywallex/utils/__init__.py
pywallex/utils/calculus.py
pywallex/webhook.py
pywallex/widget.py
pywallex-0.1.10.dist-info/LICENSE
pywallex-0.1.10.dist-info/METADATA
pywallex-0.1.10.dist-info/WHEEL
pywallex-0.1.10.dist-info/RECORD
