Metadata-Version: 2.1
Name: pywallex
Version: 0.1.10
Summary: 
Author: axdjuraev
Author-email: axdjuraev@gmail.com
Requires-Python: >=3.10,<4.0
Classifier: Programming Language :: Python :: 3
Classifier: Programming Language :: Python :: 3.10
Classifier: Programming Language :: Python :: 3.11
Requires-Dist: httpx (>=0.24.1,<0.25.0)
Requires-Dist: pydantic (==1.10.4)
Requires-Dist: python-dotenv (==0.21.1)
Requires-Dist: requests (>=2.31.0,<3.0.0)
